adux/__init__.py
adux/adux.py
adux-0.0.3.dist-info/DESCRIPTION.rst
adux-0.0.3.dist-info/METADATA
adux-0.0.3.dist-info/RECORD
adux-0.0.3.dist-info/WHEEL
adux-0.0.3.dist-info/metadata.json
adux-0.0.3.dist-info/top_level.txt
