Metadata-Version: 2.0
Name: adux
Version: 0.0.3
Summary: Test packaging
Home-page: https://github.com/adux6991/adux
Author: Adux
Author-email: adux6991@google.com
License: MIT
Keywords: sample setuptools development
Platform: UNKNOWN
Classifier: Programming Language :: Python :: 3
Classifier: Programming Language :: Python :: 3.3
Classifier: Programming Language :: Python :: 3.4
Classifier: Programming Language :: Python :: 3.5
